steel_toolbox/__init__.py
steel_toolbox/abq_tools.py
steel_toolbox/cli.py
steel_toolbox/en_tools.py
steel_toolbox/parametric_tools.py
steel_toolbox/steel_tools.py
steel_toolbox-0.1.0.dist-info/DESCRIPTION.rst
steel_toolbox-0.1.0.dist-info/METADATA
steel_toolbox-0.1.0.dist-info/RECORD
steel_toolbox-0.1.0.dist-info/WHEEL
steel_toolbox-0.1.0.dist-info/entry_points.txt
steel_toolbox-0.1.0.dist-info/metadata.json
steel_toolbox-0.1.0.dist-info/top_level.txt
