Metadata-Version: 2.0
Name: steel-toolbox
Version: 0.1.0
Summary: A collection of classes and tools used on structural steel design.
Home-page: https://github.com/manpan-1/steel_toolbox
Author: Panagiotis Manoleas
Author-email: manpan@ltu.se
License: MIT license
Keywords: structural steel eurocode
Platform: UNKNOWN
Classifier: Development Status :: 2 - Pre-Alpha
Classifier: Intended Audience :: Developers
Classifier: License :: OSI Approved :: MIT License
Classifier: Natural Language :: English
Classifier: Programming Language :: Python :: 2
Classifier: Programming Language :: Python :: 2.6
Classifier: Programming Language :: Python :: 2.7
Classifier: Programming Language :: Python :: 3
Classifier: Programming Language :: Python :: 3.3
Classifier: Programming Language :: Python :: 3.4
Classifier: Programming Language :: Python :: 3.5
Requires-Dist: Click (>=6.0)
Requires-Dist: numpy
